thtml_escape-0.1.0.dist-info/METADATA
thtml_escape-0.1.0.dist-info/WHEEL
thtml_escape.libs/libgcc_s-e52197c3.so.1
thtml_escape/__init__.py
thtml_escape/py.typed
thtml_escape/thtml_escape.cpython-39-aarch64-linux-gnu.so
thtml_escape/thtml_escape.pyi
thtml_escape-0.1.0.dist-info/RECORD
